{
  "interactionModel": {
    "languageModel": {
      "intents": [
        {
          "name": "AMAZON.CancelIntent",
          "samples": []
        },
        {
          "name": "AMAZON.HelpIntent",
          "samples": []
        },
        {
          "name": "AMAZON.StopIntent",
          "samples": []
        },
        {
          "slots": [
            {
              "name": "value",
              "type": "AMAZON.NUMBER"
            },
            {
              "name": "fromUnit",
              "type": "UNIT_TYPE"
            },
            {
              "name": "toUnit",
              "type": "UNIT_TYPE"
            }
          ],
          "name": "ConvertIntent",
          "samples": [
            "convierte {value} {fromUnit} a {toUnit}",
            "cambia {value} {fromUnit} a {toUnit}",
            "cuántos {toUnit} hay en {value} {fromUnit}"
          ]
        },
        {
          "name": "AMAZON.NavigateHomeIntent",
          "samples": []
        },
        {
          "name": "AMAZON.FallbackIntent",
          "samples": []
        }
      ],
      "types": [
        {
          "values": [
            {
              "name": {
                "value": "centimetros"
              }
            },
            {
              "name": {
                "value": "metros"
              }
            },
            {
              "name": {
                "value": "kilometros"
              }
            }
          ],
          "name": "UNIT_TYPE"
        }
      ],
      "invocationName": "conversor"
    }
  }
}